{
  "latitude": -23.55,
  "longitude": -46.625,
  "generationtime_ms": 0.12,
  "utc_offset_seconds": -10800,
  "timezone": "America/Sao_Paulo",
  "timezone_abbreviation": "-03",
  "elevation": 760,
  "current_units": {
    "time": "iso8601",
    "interval": "seconds",
    "european_aqi": "EAQI",
    "pm2_5": "μg/m³",
    "pm10": "μg/m³",
    "ozone": "μg/m³",
    "nitrogen_dioxide": "μg/m³"
  },
  "current": {
    "time": "2026-06-23T14:00",
    "interval": 3600,
    "european_aqi": 35,
    "pm2_5": 12.5,
    "pm10": 22.0,
    "ozone": 45.0,
    "nitrogen_dioxide": 18.0
  }
}
